KratosMultiphysics/CompareElementsAndConditionsUtility.pyi
KratosMultiphysics/ConstraintUtilities.pyi
KratosMultiphysics/CreateTriangleMeshFromNodes.pyi
KratosMultiphysics/EntitiesUtilities.pyi
KratosMultiphysics/Future.pyi
KratosMultiphysics/GeometricalTransformationUtilities.pyi
KratosMultiphysics/Globals.pyi
KratosMultiphysics/KratosMonitor.py
KratosMultiphysics/KratosUnittest.py
KratosMultiphysics/ModelPartOperationUtilities.pyi
KratosMultiphysics/MortarUtilities.pyi
KratosMultiphysics/PropertiesUtilities.pyi
KratosMultiphysics/SensitivityUtilities.pyi
KratosMultiphysics/SingleImportModelPart.pyi
KratosMultiphysics/SpecificationsUtilities.pyi
KratosMultiphysics/StringUtilities.pyi
KratosMultiphysics/TensorAdaptors.pyi
KratosMultiphysics/Testing.pyi
KratosMultiphysics/TimeDiscretization.pyi
KratosMultiphysics/__init__.py
KratosMultiphysics/__init__.pyi
KratosMultiphysics/analysis_stage.py
KratosMultiphysics/apply_periodic_condition_process.py
KratosMultiphysics/assign_average_master_slave_constraints_process.py
KratosMultiphysics/assign_flag_process.py
KratosMultiphysics/assign_master_slave_constraints_to_neighbours_process.py
KratosMultiphysics/assign_mpcs_to_neighbours_process.py
KratosMultiphysics/assign_scalar_input_to_conditions_process.py
KratosMultiphysics/assign_scalar_input_to_elements_process.py
KratosMultiphysics/assign_scalar_input_to_entities_process.py
KratosMultiphysics/assign_scalar_input_to_nodes_process.py
KratosMultiphysics/assign_scalar_variable_process.py
KratosMultiphysics/assign_scalar_variable_to_conditions_process.py
KratosMultiphysics/assign_scalar_variable_to_constraints_process.py
KratosMultiphysics/assign_scalar_variable_to_elements_process.py
KratosMultiphysics/assign_scalar_variable_to_entities_process.py
KratosMultiphysics/assign_scalar_variable_to_nodes_process.py
KratosMultiphysics/assign_time_derivative_process.py
KratosMultiphysics/assign_vector_by_direction_process.py
kratosmultiphysics-10.4.0.dist-info/METADATA
kratosmultiphysics-10.4.0.dist-info/WHEEL
kratosmultiphysics-10.4.0.dist-info/RECORD
