Metadata-Version: 2.4
Name: KratosMultiphysics
Version: 10.4.0
Summary:         KRATOS Multiphysics ("Kratos") is a framework for building parallel,         multi-disciplinary simulation software, aiming at modularity,         extensibility, and high performance. Kratos is written in C++,         and counts with an extensive Python interface.     
Author-email: Kratos Team <kratosmultiphysics@gmail.com>
License: BSD-4-Clause
Classifier: Intended Audience :: Developers
Classifier: Intended Audience :: Science/Research
Classifier: Natural Language :: English
Classifier: Programming Language :: C++
Classifier: Programming Language :: Python :: 3
Classifier: Topic :: Scientific/Engineering
Classifier: Topic :: Scientific/Engineering :: Mathematics
Classifier: Topic :: Scientific/Engineering :: Physics
Requires-Python: >=3.8
Requires-Dist: numpy>=1.20
